hf_hub_ctranslate2/__init__.py
hf_hub_ctranslate2/ct2_sentence_transformers.py
hf_hub_ctranslate2/translate.py
hf_hub_ctranslate2/util/__init__.py
hf_hub_ctranslate2/util/utils.py
hf_hub_ctranslate2-2.13.1.dist-info/LICENSE
hf_hub_ctranslate2-2.13.1.dist-info/METADATA
hf_hub_ctranslate2-2.13.1.dist-info/WHEEL
hf_hub_ctranslate2-2.13.1.dist-info/RECORD
