Metadata-Version: 2.1
Name: hf_hub_ctranslate2
Version: 2.13.1
Summary: Connecting Transfromers on HuggingfaceHub with CTranslate2.
License: MIT
Author: michaelfeil
Author-email: no-reply@michaelfeil.eu
Requires-Python: >=3.8,<3.13
Classifier: License :: OSI Approved :: MIT License
Classifier: Programming Language :: Python :: 3
Classifier: Programming Language :: Python :: 3.8
Classifier: Programming Language :: Python :: 3.9
Classifier: Programming Language :: Python :: 3.10
Classifier: Programming Language :: Python :: 3.11
Classifier: Programming Language :: Python :: 3.12
Provides-Extra: sentence-transformers
Requires-Dist: ctranslate2 (>=3.16.0)
Requires-Dist: huggingface-hub
Requires-Dist: numpy
Requires-Dist: sentence_transformers (==2.2.2) ; extra == "sentence-transformers"
Requires-Dist: transformers (>=4.28.0)
